parrot/QRCode.py
parrot/__init__.py
robotframework_parrot_qrcodescanner-1.0.1.dist-info/LICENSE
robotframework_parrot_qrcodescanner-1.0.1.dist-info/METADATA
robotframework_parrot_qrcodescanner-1.0.1.dist-info/WHEEL
robotframework_parrot_qrcodescanner-1.0.1.dist-info/top_level.txt
robotframework_parrot_qrcodescanner-1.0.1.dist-info/RECORD
