Metadata-Version: 2.1
Name: robotframework-parrot-qrcodescanner
Version: 1.0.1
Summary: QR Code Scanner to scan the QR images
Home-page: https://github.com/zilogic-systems/parrot
Author: Zilogic Systems
Author-email: code@zilogic.com
Classifier: Programming Language :: Python :: 3
Requires-Python: >=3.6
License-File: LICENSE
Requires-Dist: pyzbar
Requires-Dist: pillow
Requires-Dist: robotframework
